setup.cfg
setup.py
LambdaNow_Python_Client.egg-info/PKG-INFO
LambdaNow_Python_Client.egg-info/SOURCES.txt
LambdaNow_Python_Client.egg-info/dependency_links.txt
LambdaNow_Python_Client.egg-info/pbr.json
LambdaNow_Python_Client.egg-info/requires.txt
LambdaNow_Python_Client.egg-info/top_level.txt
lambdanow/__init__.py
lambdanow/channel.py
lambdanow/data.py
lambdanow/schema.py
lambdanow_python_client.egg-info/SOURCES.txt