Metadata-Version: 1.1
Name: lambdanow-python-client
Version: 0.1.3
Summary: A Python client for LambdaNow clusters
Home-page: http://www.lambdanow.com
Author: LambdaNow
Author-email: support@lambdanow.com
License: Apache 2.0
Platform: any
Classifier: Development Status :: 5 - Production/Stable
Classifier: Intended Audience :: Developers
Classifier: Intended Audience :: System Administrators
Classifier: Operating System :: POSIX :: Linux
Classifier: Topic :: Software Development
